log_tool/__init__.py
log_tool/__main__.py
log_tool/_version.py
log_tool/log_config.ini
log_tool/log_config.yaml
log_tool/py.typed
log_tool-0.0.2.dist-info/METADATA
log_tool-0.0.2.dist-info/WHEEL
log_tool-0.0.2.dist-info/entry_points.txt
log_tool-0.0.2.dist-info/licenses/LICENSE.txt
log_tool-0.0.2.dist-info/RECORD
